{
  "name": "社長専用ポモドーロ",
  "identifier": "com.suzuki.pomodoro.source",
  "apps": [
    {
      "name": "ポモドーロ",
      "bundleIdentifier": "com.suzuki.pomodorotimer",
      "developerName": "AI Studio",
      "subtitle": "社長専用ポモドーロタイマー",
      "localizedDescription": "集中→休憩を回す社長専用のポモドーロタイマー。バックグラウンド通知・アラーム・タスク履歴・統計グラフ・時間カスタム・横向き対応。",
      "iconURL": "https://raw.githubusercontent.com/kamakama1125/pomodoro-app/main/icon.png",
      "tintColor": "FF2D55",
      "category": "productivity",
      "screenshotURLs": [],
      "version": "1.3",
      "versionDate": "2026-06-12",
      "versionDescription": "アラームに「止める」ボタンを追加。手動で止めなければ10秒で自動停止。",
      "downloadURL": "https://raw.githubusercontent.com/kamakama1125/pomodoro-app/main/PomodoroTimer.ipa",
      "size": 379579,
      "versions": [
        {
          "version": "1.3",
          "date": "2026-06-12",
          "localizedDescription": "アラームに「止める」ボタンを追加。手動で止めなければ10秒で自動停止。",
          "downloadURL": "https://raw.githubusercontent.com/kamakama1125/pomodoro-app/main/PomodoroTimer.ipa",
          "size": 379579,
          "minOSVersion": "17.0"
        },
        {
          "version": "1.2",
          "date": "2026-06-12",
          "localizedDescription": "集中・休憩それぞれの終了時にアラーム音が鳴るように。マナーモードでも鳴ります。",
          "downloadURL": "https://raw.githubusercontent.com/kamakama1125/pomodoro-app/main/PomodoroTimer.ipa",
          "size": 379579,
          "minOSVersion": "17.0"
        }
      ],
      "appPermissions": {
        "entitlements": [],
        "privacy": {}
      }
    }
  ],
  "news": []
}
